isicarchive/__init__.py
isicarchive/__main__.py
isicarchive/annotation.py
isicarchive/api.py
isicarchive/colorlut.py
isicarchive/dataset.py
isicarchive/features.py
isicarchive/font.py
isicarchive/func.py
isicarchive/image.py
isicarchive/imfunc.py
isicarchive/jitfunc.py
isicarchive/numfunc.py
isicarchive/reedsolo.py
isicarchive/sampler.py
isicarchive/segmentation.py
isicarchive/statsimage.py
isicarchive/study.py
isicarchive/vars.py
isicarchive/version.py
isicarchive/etc/font_calibri.npz
isicarchive/tests/__init__.py
isicarchive/tests/api.py
isicarchive-0.4.11.dist-info/LICENSE
isicarchive-0.4.11.dist-info/METADATA
isicarchive-0.4.11.dist-info/WHEEL
isicarchive-0.4.11.dist-info/top_level.txt
isicarchive-0.4.11.dist-info/RECORD
