Metadata-Version: 2.1
Name: isicarchive
Version: 0.4.11
Summary: ISIC Archive API
Home-page: https://github.com/neuroelf/isicarchive
Author: Jochen Weber
Author-email: weberj3@mskcc.org
License: MIT
Platform: UNKNOWN
Classifier: Development Status :: 3 - Alpha
Classifier: Intended Audience :: Developers
Classifier: Natural Language :: English
Classifier: Programming Language :: Python :: 3
Classifier: License :: OSI Approved :: MIT License
Classifier: Operating System :: OS Independent
Requires-Python: >=3.6
Requires-Dist: imageio (>=2.5.0)
Requires-Dist: ipython (>=7.1.0)
Requires-Dist: ipywidgets (>=7.1.0)
Requires-Dist: matplotlib (>=3.1.0)
Requires-Dist: numba (>=0.45.1)
Requires-Dist: numpy (>=1.16.2)
Requires-Dist: scipy (>=1.3.1)
Requires-Dist: requests (>=2.22.0)
